disno/__init__.py
disno/client.py
disno/enums.py
disno/managers.py
disno/test.py
disno/utils.py
disno/http/__init__.py
disno/http/client.py
disno/http/enums.py
disno/http/route.py
disno/http/utils.py
disno/http/endpoints/__init__.py
disno/http/endpoints/channels.py
disno/http/endpoints/guilds.py
disno/http/endpoints/messages.py
disno/http/endpoints/oauth2.py
disno/http/endpoints/reactions.py
disno/http/endpoints/users.py
disno/objects/__init__.py
disno/objects/baseclass.py
disno/objects/user.py
disno-0.1.dist-info/LICENSE
disno-0.1.dist-info/METADATA
disno-0.1.dist-info/WHEEL
disno-0.1.dist-info/top_level.txt
disno-0.1.dist-info/RECORD
