Metadata-Version: 2.1
Name: disno
Version: 0.1
Summary: Another discord api wrapper just ignore
Home-page: https://github.com/QwireDev/disno
Author: Middledot
Author-email: middledot.productions@gmail.com
License: UNKNOWN
Project-URL: Issue Tracker, https://github.com/QwireDev/disno/issues
Platform: UNKNOWN
Classifier: Development Status :: 1 - Planning
Classifier: Programming Language :: Python :: 3
Classifier: License :: OSI Approved :: MIT License
Classifier: Operating System :: OS Independent
Requires-Python: >=3.6
License-File: LICENSE
